{"ts": 1778043600.1122572, "data": {"hits_allowed_avg": 6.12, "tb_allowed_avg": 10.88, "hr_allowed_avg": 0.75, "strikeouts_avg": 2.75, "k_std": 1.3, "xwoba_allowed": 0.338, "hard_hit_allowed": 0.348, "barrel_allowed": 0.072, "hand": "R", "games_used": 5, "first_inning_runs_avg": 0.33, "nrfi_solo_rate": 0.667, "splits": {"vs_L": {"hits_allowed_avg": 4.0, "hr_allowed_avg": 0.6, "samples": 188}, "vs_R": {"hits_allowed_avg": 1.4, "hr_allowed_avg": 0.0, "samples": 149}}, "fb_pct": 0.49, "fb_velo": 90.8}}