{"ts": 1779341124.3227983, "data": {"hits_avg": 0.4, "hr_avg": 0.06, "tb_avg": 0.6, "rbi_avg": 0.24, "hits_std": 0.6, "tb_std": 1.05, "iso_power": 0.5, "contact_rate": 0.162, "hand": "R", "hot_ratio": 1.0, "games_used": 20, "hits_l15_avg": 0.4, "hits_season_avg": 0.4, "games_l15": 15, "games_season": 20, "xhits_avg": 0.193, "xtb_avg": 2.564, "barrel_rate": 0.0, "fly_ball_rate": 0.448, "hard_hit_rate": 0.172, "bbe_per_game": 1.38, "splits": {"vs_L": {"hits_avg": 0.29, "hr_avg": 0.143, "tb_avg": 0.86, "samples": 35}, "vs_R": {"hits_avg": 0.35, "hr_avg": 0.0, "tb_avg": 0.35, "samples": 133}}}}