{"ts": 1779459610.359928, "data": {"hits_avg": 0.98, "hr_avg": 0.01, "tb_avg": 1.17, "rbi_avg": 0.47, "hits_std": 0.84, "tb_std": 1.14, "iso_power": 0.208, "contact_rate": 0.196, "hand": "R", "hot_ratio": 1.24, "games_used": 56, "hits_l15_avg": 1.07, "hits_season_avg": 0.86, "games_l15": 15, "games_season": 56, "xhits_avg": 0.959, "xtb_avg": 8.765, "barrel_rate": 0.015, "fly_ball_rate": 0.362, "hard_hit_rate": 0.3, "bbe_per_game": 2.94, "splits": {"vs_L": {"hits_avg": 0.53, "hr_avg": 0.028, "tb_avg": 0.72, "samples": 348}, "vs_R": {"hits_avg": 0.64, "hr_avg": 0.0, "tb_avg": 0.71, "samples": 424}}}}