{"ts": 1779503012.126008, "data": {"hits_avg": 0.61, "hr_avg": 0.08, "tb_avg": 0.98, "rbi_avg": 0.36, "hits_std": 0.86, "tb_std": 1.63, "iso_power": 0.727, "contact_rate": 0.16, "hand": "R", "hot_ratio": 0.96, "games_used": 53, "hits_l15_avg": 0.6, "hits_season_avg": 0.62, "games_l15": 15, "games_season": 53, "xhits_avg": 0.701, "xtb_avg": 6.668, "barrel_rate": 0.09, "fly_ball_rate": 0.26, "hard_hit_rate": 0.36, "bbe_per_game": 2.39, "splits": {"vs_L": {"hits_avg": 0.28, "hr_avg": 0.062, "tb_avg": 0.62, "samples": 253}, "vs_R": {"hits_avg": 0.51, "hr_avg": 0.064, "tb_avg": 0.79, "samples": 477}}}}