{"ts": 1777844889.7226682, "data": {"hits_avg": 1.64, "hr_avg": 0.73, "tb_avg": 4.0, "rbi_avg": 1.45, "hits_std": 0.93, "tb_std": 2.33, "iso_power": 1.333, "contact_rate": 0.221, "hand": "R", "hot_ratio": 1.33, "games_used": 8, "xhits_avg": 1.135, "xtb_avg": 8.951, "barrel_rate": 0.21, "fly_ball_rate": 0.54, "hard_hit_rate": 0.47, "bbe_per_game": 3.62, "splits": {"vs_L": {"hits_avg": 0.62, "hr_avg": 0.143, "tb_avg": 1.1, "samples": 194}, "vs_R": {"hits_avg": 0.74, "hr_avg": 0.29, "tb_avg": 1.81, "samples": 351}}}}