{"ts": 1777998543.5828302, "data": {"hits_avg": 1.36, "hr_avg": 0.64, "tb_avg": 3.36, "rbi_avg": 1.23, "hits_std": 0.93, "tb_std": 2.33, "iso_power": 1.333, "contact_rate": 0.217, "hand": "R", "hot_ratio": 0.67, "games_used": 8, "xhits_avg": 1.074, "xtb_avg": 8.711, "barrel_rate": 0.198, "fly_ball_rate": 0.545, "hard_hit_rate": 0.455, "bbe_per_game": 3.5, "splits": {"vs_L": {"hits_avg": 0.59, "hr_avg": 0.136, "tb_avg": 1.05, "samples": 197}, "vs_R": {"hits_avg": 0.74, "hr_avg": 0.29, "tb_avg": 1.81, "samples": 354}}}}