{"ts": 1779459597.7660916, "data": {"hits_avg": 0.99, "hr_avg": 0.01, "tb_avg": 1.27, "rbi_avg": 0.48, "hits_std": 0.83, "tb_std": 1.19, "iso_power": 0.2, "contact_rate": 0.235, "hand": "L", "hot_ratio": 0.88, "games_used": 61, "hits_l15_avg": 0.93, "hits_season_avg": 1.07, "games_l15": 15, "games_season": 61, "xhits_avg": 0.952, "xtb_avg": 6.318, "barrel_rate": 0.0, "fly_ball_rate": 0.199, "hard_hit_rate": 0.154, "bbe_per_game": 3.36, "splits": {"vs_L": {"hits_avg": 0.41, "hr_avg": 0.0, "tb_avg": 0.49, "samples": 217}, "vs_R": {"hits_avg": 0.84, "hr_avg": 0.017, "tb_avg": 1.02, "samples": 562}}}}