{"ts": 1777520134.521001, "data": {"hits_avg": 0.82, "hr_avg": 0.36, "tb_avg": 2.09, "rbi_avg": 0.73, "hits_std": 0.71, "tb_std": 2.07, "iso_power": 1.667, "contact_rate": 0.173, "hand": "R", "hot_ratio": 1.33, "games_used": 8, "xhits_avg": 0.758, "xtb_avg": 6.748, "barrel_rate": 0.089, "fly_ball_rate": 0.429, "hard_hit_rate": 0.411, "bbe_per_game": 2.25, "splits": {"vs_L": {"hits_avg": 0.33, "hr_avg": 0.167, "tb_avg": 0.94, "samples": 117}, "vs_R": {"hits_avg": 0.32, "hr_avg": 0.04, "tb_avg": 0.48, "samples": 257}}}}