{"ts": 1779601161.8575118, "data": {"hits_avg": 0.62, "hr_avg": 0.03, "tb_avg": 0.88, "rbi_avg": 0.33, "hits_std": 0.7, "tb_std": 1.46, "iso_power": 0.634, "contact_rate": 0.173, "hand": "L", "hot_ratio": 0.69, "games_used": 53, "hits_l15_avg": 0.53, "hits_season_avg": 0.77, "games_l15": 15, "games_season": 53, "xhits_avg": 0.863, "xtb_avg": 7.592, "barrel_rate": 0.08, "fly_ball_rate": 0.372, "hard_hit_rate": 0.372, "bbe_per_game": 2.39, "splits": {"vs_L": {"hits_avg": 0.39, "hr_avg": 0.036, "tb_avg": 0.68, "samples": 184}, "vs_R": {"hits_avg": 0.6, "hr_avg": 0.08, "tb_avg": 0.96, "samples": 521}}}}