{"ts": 1779339511.0532074, "data": {"hits_avg": 1.73, "hr_avg": 0.27, "tb_avg": 2.82, "rbi_avg": 1.06, "hits_std": 1.19, "tb_std": 2.13, "iso_power": 0.727, "contact_rate": 0.131, "hand": "L", "hot_ratio": 1.94, "games_used": 8, "xhits_avg": 1.298, "xtb_avg": 16.337, "barrel_rate": 0.277, "fly_ball_rate": 0.305, "hard_hit_rate": 0.638, "bbe_per_game": 2.75, "splits": {"vs_L": {"hits_avg": 0.39, "hr_avg": 0.097, "tb_avg": 0.81, "samples": 269}, "vs_R": {"hits_avg": 0.82, "hr_avg": 0.205, "tb_avg": 1.59, "samples": 542}}}}