{"ts": 1777994806.570132, "data": {"hits_avg": 1.18, "hr_avg": 0.27, "tb_avg": 2.36, "rbi_avg": 0.83, "hits_std": 1.07, "tb_std": 2.93, "iso_power": 1.0, "contact_rate": 0.26, "hand": "L", "hot_ratio": 1.67, "games_used": 8, "xhits_avg": 1.269, "xtb_avg": 7.463, "barrel_rate": 0.036, "fly_ball_rate": 0.25, "hard_hit_rate": 0.5, "bbe_per_game": 3.12, "splits": {"vs_L": {"hits_avg": 0.83, "hr_avg": 0.0, "tb_avg": 1.5, "samples": 31}, "vs_R": {"hits_avg": 0.62, "hr_avg": 0.25, "tb_avg": 1.38, "samples": 73}}}}