{"ts": 1779601142.7592769, "data": {"hits_avg": 0.89, "hr_avg": 0.1, "tb_avg": 1.4, "rbi_avg": 0.51, "hits_std": 0.84, "tb_std": 1.95, "iso_power": 0.646, "contact_rate": 0.225, "hand": "R", "hot_ratio": 0.94, "games_used": 52, "hits_l15_avg": 0.87, "hits_season_avg": 0.92, "games_l15": 15, "games_season": 52, "xhits_avg": 1.006, "xtb_avg": 6.858, "barrel_rate": 0.083, "fly_ball_rate": 0.274, "hard_hit_rate": 0.414, "bbe_per_game": 3.06, "splits": {"vs_L": {"hits_avg": 0.48, "hr_avg": 0.037, "tb_avg": 0.63, "samples": 192}, "vs_R": {"hits_avg": 0.74, "hr_avg": 0.149, "tb_avg": 1.32, "samples": 440}}}}