{"ts": 1777779029.9811006, "data": {"hits_avg": 1.45, "hr_avg": 0.09, "tb_avg": 2.0, "rbi_avg": 0.77, "hits_std": 0.52, "tb_std": 1.25, "iso_power": 0.545, "contact_rate": 0.22, "hand": "R", "hot_ratio": 1.21, "games_used": 8, "xhits_avg": 1.238, "xtb_avg": 9.361, "barrel_rate": 0.053, "fly_ball_rate": 0.242, "hard_hit_rate": 0.547, "bbe_per_game": 3.25, "splits": {"vs_L": {"hits_avg": 0.36, "hr_avg": 0.071, "tb_avg": 0.71, "samples": 117}, "vs_R": {"hits_avg": 0.97, "hr_avg": 0.1, "tb_avg": 1.57, "samples": 345}}}}