{"ts": 1777584580.8582504, "data": {"hits_avg": 1.27, "hr_avg": 0.36, "tb_avg": 2.55, "rbi_avg": 0.94, "hits_std": 0.83, "tb_std": 2.33, "iso_power": 0.778, "contact_rate": 0.178, "hand": "L", "hot_ratio": 1.48, "games_used": 8, "xhits_avg": 1.245, "xtb_avg": 14.069, "barrel_rate": 0.212, "fly_ball_rate": 0.385, "hard_hit_rate": 0.481, "bbe_per_game": 3.25, "splits": {"vs_L": {"hits_avg": 0.2, "hr_avg": 0.1, "tb_avg": 0.5, "samples": 95}, "vs_R": {"hits_avg": 1.13, "hr_avg": 0.133, "tb_avg": 1.73, "samples": 202}}}}