{"ts": 1779339514.9115508, "data": {"hits_avg": 0.82, "hr_avg": 0.0, "tb_avg": 1.0, "rbi_avg": 0.39, "hits_std": 0.71, "tb_std": 0.99, "iso_power": 0.167, "contact_rate": 0.183, "hand": "L", "hot_ratio": 1.33, "games_used": 8, "xhits_avg": 0.936, "xtb_avg": 9.574, "barrel_rate": 0.158, "fly_ball_rate": 0.43, "hard_hit_rate": 0.526, "bbe_per_game": 2.62, "splits": {"vs_L": {"hits_avg": 0.53, "hr_avg": 0.118, "tb_avg": 1.09, "samples": 322}, "vs_R": {"hits_avg": 0.71, "hr_avg": 0.235, "tb_avg": 1.53, "samples": 413}}}}