{"ts": 1777844983.720389, "data": {"hits_avg": 1.27, "hr_avg": 0.18, "tb_avg": 1.82, "rbi_avg": 0.75, "hits_std": 0.89, "tb_std": 1.77, "iso_power": 0.6, "contact_rate": 0.132, "hand": "L", "hot_ratio": 1.07, "games_used": 8, "xhits_avg": 0.966, "xtb_avg": 12.107, "barrel_rate": 0.143, "fly_ball_rate": 0.319, "hard_hit_rate": 0.516, "bbe_per_game": 2.38, "splits": {"vs_L": {"hits_avg": 0.46, "hr_avg": 0.042, "tb_avg": 0.67, "samples": 176}, "vs_R": {"hits_avg": 0.8, "hr_avg": 0.086, "tb_avg": 1.31, "samples": 472}}}}