{"ts": 1779601184.5932662, "data": {"hits_avg": 0.53, "hr_avg": 0.11, "tb_avg": 0.99, "rbi_avg": 0.35, "hits_std": 0.72, "tb_std": 1.32, "iso_power": 0.625, "contact_rate": 0.172, "hand": "L", "hot_ratio": 1.03, "games_used": 62, "hits_l15_avg": 0.53, "hits_season_avg": 0.52, "games_l15": 15, "games_season": 62, "xhits_avg": 0.688, "xtb_avg": 6.097, "barrel_rate": 0.1, "fly_ball_rate": 0.392, "hard_hit_rate": 0.492, "bbe_per_game": 2.2, "splits": {"vs_L": {"hits_avg": 0.26, "hr_avg": 0.0, "tb_avg": 0.35, "samples": 190}, "vs_R": {"hits_avg": 0.43, "hr_avg": 0.071, "tb_avg": 0.73, "samples": 584}}}}