{"ts": 1779601181.2930722, "data": {"hits_avg": 1.13, "hr_avg": 0.13, "tb_avg": 1.72, "rbi_avg": 0.65, "hits_std": 0.74, "tb_std": 1.47, "iso_power": 0.667, "contact_rate": 0.197, "hand": "R", "hot_ratio": 1.47, "games_used": 66, "hits_l15_avg": 1.27, "hits_season_avg": 0.86, "games_l15": 15, "games_season": 66, "xhits_avg": 1.23, "xtb_avg": 10.878, "barrel_rate": 0.132, "fly_ball_rate": 0.413, "hard_hit_rate": 0.437, "bbe_per_game": 3.3, "splits": {"vs_L": {"hits_avg": 0.53, "hr_avg": 0.111, "tb_avg": 1.03, "samples": 248}, "vs_R": {"hits_avg": 0.6, "hr_avg": 0.063, "tb_avg": 0.92, "samples": 715}}}}