{"ts": 1778043612.5303936, "data": {"hits_avg": 0.91, "hr_avg": 0.18, "tb_avg": 1.73, "rbi_avg": 0.61, "hits_std": 1.07, "tb_std": 2.95, "iso_power": 1.125, "contact_rate": 0.25, "hand": "R", "hot_ratio": 0.67, "games_used": 8, "xhits_avg": 1.131, "xtb_avg": 8.915, "barrel_rate": 0.143, "fly_ball_rate": 0.265, "hard_hit_rate": 0.469, "bbe_per_game": 3.25, "splits": {"vs_L": {"hits_avg": 0.57, "hr_avg": 0.0, "tb_avg": 0.71, "samples": 55}, "vs_R": {"hits_avg": 0.73, "hr_avg": 0.2, "tb_avg": 1.53, "samples": 140}}}}