{"ts": 1777520096.5684984, "data": {"hits_avg": 1.18, "hr_avg": 0.0, "tb_avg": 1.64, "rbi_avg": 0.58, "hits_std": 0.93, "tb_std": 1.6, "iso_power": 0.375, "contact_rate": 0.13, "hand": "R", "hot_ratio": 1.67, "games_used": 8, "xhits_avg": 0.863, "xtb_avg": 10.708, "barrel_rate": 0.116, "fly_ball_rate": 0.407, "hard_hit_rate": 0.372, "bbe_per_game": 2.5, "splits": {"vs_L": {"hits_avg": 0.5, "hr_avg": 0.062, "tb_avg": 0.75, "samples": 172}, "vs_R": {"hits_avg": 0.67, "hr_avg": 0.111, "tb_avg": 1.25, "samples": 511}}}}